{"Employees":[{"BINH TRA":[{"peopleID":1,"employeeID":1,"relativeID":0,"name":"BINH TRA","sex":"MALE","team":"BV02","phone":"0910000001","description":"serious, lazy, honest"}]},{"ANH PHAN":[{"peopleID":4,"employeeID":4,"relativeID":0,"name":"ANH PHAN","sex":"MALE","team":"DA","phone":"0910000002","description":"polite, kind, friendly"}]},{"HUY VO":[{"peopleID":3,"employeeID":3,"relativeID":0,"name":"HUY VO","sex":"MALE","team":"TechOne","phone":"0910000000","description":"dishonest, smart, shy"}]}]}